{
  "PayButton.title": "Betal",
  "Navigation.back": "< Back",

  "DropInViewController.title": "Payment",
  "DropInViewController.successfulPayment": "Betalingen er fullført",
  "DropInViewController.cardinalAuthenticationError": "Det inntraff en feil",

  "CardNumberInputView.title": "Kortnummer",
  "CardNumberInputView.placeholder": "xxxx xxxx xxxx xxxx",
  "CardNumberInputView.error": "Invalid card number",
  "CardNumberInputView.emptyError": "Kortnummer is required",

  "CvcInputView.title": "Sikkerhetskode",
  "CvcInputView.placeholder3": "***",
  "CvcInputView.placeholder4": "****",
  "CvcInputView.placeholderPiba": "N/A",
  "CvcInputView.error": "Invalid security code",
  "CvcInputView.emptyError": "Sikkerhetskode is required",

  "ExpiryDateInputView.title": "Utløpsdato",
  "ExpiryDateInputView.placeholder": "MM/YY",
  "ExpiryDateInputView.error": "Invalid expiry date",
  "ExpiryDateInputView.emptyError": "Utløpsdato is required",

  "AddCardButton.title": "Add card",

  "Alerts.processing": "Behandler",
}
